scez/__init__.py
scez/diffexp.py
scez/preprocess.py
scez/representation.py
scez/utils.py
scez/tests/__init__.py
scez/tests/test_scez.py
scez-0.2.1.dist-info/METADATA
scez-0.2.1.dist-info/WHEEL
scez-0.2.1.dist-info/licenses/LICENSE
scez-0.2.1.dist-info/RECORD
