Metadata-Version: 2.4
Name: scez
Version: 0.2.1
Summary: Single Cell Analysis, Easy Mode!
Project-URL: Source, https://github.com/abearab/scez
Author-email: Abe Arab <abarbiology@gmail.com>
License: MIT
License-File: LICENSE
Classifier: License :: OSI Approved :: MIT License
Requires-Python: <4.0,>=3.9
Provides-Extra: test
Requires-Dist: pytest; extra == 'test'
Requires-Dist: tomli; extra == 'test'
